{
    "name": "Iji",
    "stagesAmount": 3,
   
    "stages":
    [{
        "Description": "Meet Iji at the Road to the Manor site of grace in Liurnia",
        "Location": "TBD",
       
        "Boss_Requirements" : ["None"],
        "Quest_Requirements" : ["None"],

        "Boss_Lockouts": ["None"],
        "Area_Lockouts": ["None"],
        "Npc_Lockout": ["None"],
        "Quest_Lockout": ["None"],
        "Event_Lockout": ["None"],
       
        "Boss_Skip": ["None"],
        "Area_Skip": ["None"],
        "Npc_Skip": ["None"],
        "Quest_Skip": ["None"],
        "Event_Skip": ["None"]
    },
    {
        "Description": "After agreeing to serve Ranni in Ranni's rise, talk to Iji",
        "Location": "TBD",
       
        "Boss_Requirements" : ["None"],
        "Quest_Requirements" : ["None"],

        "Boss_Lockouts": ["None"],
        "Area_Lockouts": ["None"],
        "Npc_Lockout": ["None"],
        "Quest_Lockout": ["None"],
        "Event_Lockout": ["None"],
       
        "Boss_Skip": ["None"],
        "Area_Skip": ["None"],
        "Npc_Skip": ["None"],
        "Quest_Skip": ["None"],
        "Event_Skip": ["None"]
    },
    {
        "Description": "After completing Blaidd's questline, talk to Iji",
        "Location": "TBD",
       
        "Boss_Requirements" : ["None"],
        "Quest_Requirements" : ["None"],

        "Boss_Lockouts": ["None"],
        "Area_Lockouts": ["None"],
        "Npc_Lockout": ["None"],
        "Quest_Lockout": ["None"],
        "Event_Lockout": ["None"],
       
        "Boss_Skip": ["None"],
        "Area_Skip": ["None"],
        "Npc_Skip": ["None"],
        "Quest_Skip": ["None"],
        "Event_Skip": ["None"]
    }]

     
   
}